sw4iot_etcd/__init__.py
sw4iot_etcd/sw4iot_etcd.py
sw4iot_etcd-0.0.1.dist-info/DESCRIPTION.rst
sw4iot_etcd-0.0.1.dist-info/METADATA
sw4iot_etcd-0.0.1.dist-info/RECORD
sw4iot_etcd-0.0.1.dist-info/WHEEL
sw4iot_etcd-0.0.1.dist-info/metadata.json
sw4iot_etcd-0.0.1.dist-info/top_level.txt
