Metadata-Version: 2.0
Name: sw4iot-etcd
Version: 0.0.1
Summary: Etcd of SOFTWAY4IoT
Home-page: https://github.com/sw4iot/sw4iot-etcd
Author: SOFTWAY4IoT
Author-email: softway4iot@gmail.com
License: Apache Software License
Keywords: sw4iot-etcd
Platform: UNKNOWN
Classifier: Development Status :: 3 - Alpha
Classifier: License :: OSI Approved :: Apache Software License
Classifier: Intended Audience :: Developers
Classifier: Natural Language :: English
Classifier: Operating System :: OS Independent
Classifier: Programming Language :: Python :: 2.7
Classifier: Programming Language :: Python :: 3.4
Classifier: Programming Language :: Python :: 3.5
Requires-Dist: etcd3 (>=0.8.1)
